flash_colsum/__init__.py
flash_colsum/baselines.py
flash_colsum/kernel_causal.py
flash_colsum/kernel_noncausal.py
flash_colsum/kernel_noncausal_batched.py
flash_colsum/ops.py
flash_colsum-0.1.0.dist-info/licenses/LICENSE
flash_colsum-0.1.0.dist-info/METADATA
flash_colsum-0.1.0.dist-info/WHEEL
flash_colsum-0.1.0.dist-info/top_level.txt
flash_colsum-0.1.0.dist-info/RECORD
