Metadata-Version: 2.4
Name: flash-colsum
Version: 0.1.0
Summary: Fast attention column-sum primitives with Triton kernels
Author: Samir Khaki
License: Apache License
Project-URL: Homepage, https://github.com/z-lab/flash-colsum
Project-URL: Issues, https://github.com/z-lab/flash-colsum/issues
Requires-Python: >=3.10
License-File: LICENSE
Requires-Dist: torch>=2.1
Requires-Dist: triton>=3.0.0
Requires-Dist: pytest>=7.0
Requires-Dist: pytest-cov>=4.0
Requires-Dist: matplotlib>=3.7
Requires-Dist: rich>=13.7
Dynamic: license-file
